autodiff/__init__.py
autodiff/autodiff.py
tests/__init__.py
tests/test_autodiff.py
yaadl-1.0.1.dist-info/METADATA
yaadl-1.0.1.dist-info/WHEEL
yaadl-1.0.1.dist-info/top_level.txt
yaadl-1.0.1.dist-info/RECORD
