Metadata-Version: 2.1
Name: yaadl
Version: 1.0.1
Summary: Yet Another Automatic Differentation Library
Home-page: UNKNOWN
Author: Murat Koptur
License: UNKNOWN
Platform: UNKNOWN
Classifier: Development Status :: 4 - Beta
Classifier: Intended Audience :: Science/Research
Classifier: License :: OSI Approved :: GNU General Public License v3 (GPLv3)
Classifier: Operating System :: OS Independent
Classifier: Programming Language :: Python :: 3.10
Classifier: Topic :: Scientific/Engineering
